wallabagapi/__init__.py
wallabagapi/core.py
wallabagapi/wallabag_test.py
wallabagapi-1.3.2.dist-info/LICENSE
wallabagapi-1.3.2.dist-info/METADATA
wallabagapi-1.3.2.dist-info/WHEEL
wallabagapi-1.3.2.dist-info/top_level.txt
wallabagapi-1.3.2.dist-info/RECORD
