Metadata-Version: 2.1
Name: wallabagapi
Version: 1.3.2
Summary: Wallabag API to add every pages you want to your Wallabag account
Home-page: https://gitlab.com/foxmask/wallabagapi
Author: 폭스마스크
Author-email: foxmask+git@pm.me
License: WTFPL
Platform: UNKNOWN
Classifier: Development Status :: 5 - Production/Stable
Classifier: Intended Audience :: Developers
Classifier: License :: Public Domain
Classifier: Operating System :: OS Independent
Classifier: Programming Language :: Python
Classifier: Programming Language :: Python :: 3.8
Classifier: Topic :: Internet
Classifier: Topic :: Communications
Requires-Dist: httpx (>=0.18.2)
